{
	"response": {
		"header": {
			"resultCode": "0000",
			"resultMsg": "OK"
		},
		"body": {
			"pageNo": 1,
			"totalCount": 690,
			"items": {
				"item": [
					{
						"readcount": 0,
						"addr2": "(가회동)",
						"addr1": "서울특별시 종로구 북촌로 57",
						"contentid": 2733967,
						"firstimage2": "http:\/\/tong.visitkorea.or.kr\/cms\/resource\/61\/2780561_image2_1.png",
						"title": "가회동성당",
						"areacode": 1,
						"createdtime": 20210817094103,
						"mapy": 37.5820858828,
						"contenttypeid": 12,
						"mapx": 126.9846616856,
						"zipcode": "03052",
						"cat2": "A0201",
						"cat3": "A02010900",
						"modifiedtime": 20211201163312,
						"cat1": "A02",
						"mlevel": 6,
						"sigungucode": 23,
						"firstimage": "http:\/\/tong.visitkorea.or.kr\/cms\/resource\/61\/2780561_image2_1.png"
					},
					{
						"readcount": 0,
						"addr2": "(답십리동)",
						"addr1": "서울특별시 동대문구 서울시립대로2길 59",
						"contentid": 2763807,
						"firstimage2": "http:\/\/tong.visitkorea.or.kr\/cms\/resource\/49\/2773049_image3_1.jpg",
						"title": "간데메공원",
						"areacode": 1,
						"createdtime": 20211027143001,
						"mapy": 37.5728520032,
						"contenttypeid": 12,
						"mapx": 127.0490977427,
						"zipcode": "02595",
						"cat2": "A0202",
						"cat3": "A02020700",
						"modifiedtime": 20211111104249,
						"cat1": "A02",
						"mlevel": 6,
						"sigungucode": 11,
						"firstimage": "http:\/\/tong.visitkorea.or.kr\/cms\/resource\/49\/2773049_image2_1.jpg"
					},
					{
						"readcount": 30919,
						"addr1": "서울 양천구 신정동 162-56",
						"contentid": 1116925,
						"firstimage2": "http:\/\/tong.visitkorea.or.kr\/cms\/resource\/62\/2612062_image2_1.bmp",
						"title": "갈산근린공원",
						"areacode": 1,
						"createdtime": 20101026133528,
						"mapy": 37.5061176314,
						"contenttypeid": 12,
						"mapx": 126.8684105358,
						"zipcode": "08104",
						"cat2": "A0202",
						"cat3": "A02020700",
						"modifiedtime": 20210715165604,
						"cat1": "A02",
						"mlevel": 6,
						"sigungucode": 19,
						"firstimage": "http:\/\/tong.visitkorea.or.kr\/cms\/resource\/62\/2612062_image2_1.bmp"
					},
					{
						"readcount": 24182,
						"addr2": "(충신동)",
						"addr1": "서울특별시 종로구 율곡로23길 16",
						"contentid": 294439,
						"firstimage2": "http:\/\/tong.visitkorea.or.kr\/cms\/resource\/85\/2031885_image3_1.jpg",
						"title": "감로암(서울)",
						"areacode": 1,
						"createdtime": 20071126155251,
						"mapy": 37.5753148419,
						"contenttypeid": 12,
						"mapx": 127.0066015446,
						"zipcode": "03099",
						"cat2": "A0201",
						"cat3": "A02010800",
						"modifiedtime": 20211129165202,
						"cat1": "A02",
						"mlevel": 6,
						"sigungucode": 23,
						"firstimage": "http:\/\/tong.visitkorea.or.kr\/cms\/resource\/85\/2031885_image2_1.jpg"
					},
					{
						"readcount": 31967,
						"addr2": "(역삼동)",
						"addr1": "서울특별시 강남구 역삼동",
						"contentid": 264570,
						"firstimage2": "http:\/\/tong.visitkorea.or.kr\/cms\/resource\/08\/1984608_image3_1.jpg",
						"title": "강남",
						"areacode": 1,
						"createdtime": 20050623134701,
						"mapy": 37.4970465429,
						"contenttypeid": 12,
						"mapx": 127.0281573537,
						"zipcode": "06232",
						"cat2": "A0203",
						"cat3": "A02030600",
						"modifiedtime": 20210601104414,
						"cat1": "A02",
						"mlevel": 6,
						"sigungucode": 1,
						"firstimage": "http:\/\/tong.visitkorea.or.kr\/cms\/resource\/08\/1984608_image2_1.jpg"
					},
					{
						"readcount": 4076,
						"addr2": "(삼성동)",
						"addr1": "서울특별시 강남구 영동대로 513",
						"contentid": 2456536,
						"title": "강남 마이스 관광특구",
						"areacode": 1,
						"createdtime": 20161214141140,
						"mapy": 37.5118092746,
						"contenttypeid": 12,
						"mapx": 127.0591318945,
						"zipcode": "06164",
						"cat2": "A0202",
						"cat3": "A02020200",
						"modifiedtime": 20210208173916,
						"cat1": "A02",
						"mlevel": 6,
						"sigungucode": 1
					},
					{
						"readcount": 17817,
						"addr1": "서울특별시 강남구 압구정로 161",
						"contentid": 1949905,
						"firstimage2": "http:\/\/tong.visitkorea.or.kr\/cms\/resource\/75\/1258175_image3_1.jpg",
						"title": "강남 시티투어 (트롤리버스)",
						"areacode": 1,
						"createdtime": 20140922180533,
						"mapy": 37.5269874797,
						"contenttypeid": 12,
						"mapx": 127.0264344408,
						"zipcode": "06001",
						"cat2": "A0203",
						"cat3": "A02030400",
						"modifiedtime": 20210115092136,
						"cat1": "A02",
						"mlevel": 6,
						"sigungucode": 1,
						"firstimage": "http:\/\/tong.visitkorea.or.kr\/cms\/resource\/75\/1258175_image2_1.jpg"
					},
					{
						"readcount": 25725,
						"addr1": "서울특별시 강동구 천호동",
						"contentid": 127377,
						"firstimage2": "http:\/\/tong.visitkorea.or.kr\/cms\/resource\/60\/720460_image3_1.jpg",
						"title": "강동예찬시비",
						"areacode": 1,
						"createdtime": 20040227000000,
						"mapy": 37.5426873535,
						"contenttypeid": 12,
						"mapx": "127.1207004140",
						"zipcode": "05246",
						"cat2": "A0205",
						"cat3": "A02050200",
						"modifiedtime": 20210322170832,
						"cat1": "A02",
						"mlevel": 6,
						"sigungucode": 2,
						"firstimage": "http:\/\/tong.visitkorea.or.kr\/cms\/resource\/60\/720460_image2_1.jpg"
					},
					{
						"readcount": 32731,
						"addr2": "(구의동)",
						"addr1": "서울특별시 광진구 구의강변로 45",
						"contentid": 128961,
						"firstimage2": "http:\/\/tong.visitkorea.or.kr\/cms\/resource\/13\/1984613_image3_1.jpg",
						"title": "강변스파랜드",
						"areacode": 1,
						"createdtime": 20060508000000,
						"mapy": 37.5348266305,
						"contenttypeid": 12,
						"mapx": 127.0916116181,
						"zipcode": "05049",
						"cat2": "A0202",
						"cat3": "A02020400",
						"modifiedtime": 20210712160610,
						"cat1": "A02",
						"mlevel": 6,
						"sigungucode": 6,
						"firstimage": "http:\/\/tong.visitkorea.or.kr\/cms\/resource\/13\/1984613_image2_1.jpg"
					},
					{
						"readcount": 42094,
						"addr2": "(방화동)",
						"addr1": "서울특별시 강서구 양천로27길 279-23",
						"contentid": 809490,
						"firstimage2": "http:\/\/tong.visitkorea.or.kr\/cms\/resource\/81\/1894481_image3_1.jpg",
						"title": "강서습지생태공원",
						"areacode": 1,
						"createdtime": 20090924000047,
						"mapy": 37.5860879769,
						"contenttypeid": 12,
						"mapx": 126.8171490732,
						"zipcode": "07518",
						"cat2": "A0101",
						"cat3": "A01010500",
						"modifiedtime": 20210127182349,
						"cat1": "A01",
						"mlevel": 6,
						"sigungucode": 4,
						"firstimage": "http:\/\/tong.visitkorea.or.kr\/cms\/resource\/81\/1894481_image2_1.jpg"
					}
				]
			},
			"numOfRows": 10
		}
	}
}